setup.py
bitquant/__init__.py
bitquant.egg-info/PKG-INFO
bitquant.egg-info/SOURCES.txt
bitquant.egg-info/dependency_links.txt
bitquant.egg-info/requires.txt
bitquant.egg-info/top_level.txt
bitquant/api/__init__.py
bitquant/api/clss.py
bitquant/api/frmt.py
bitquant/api/rest.py
bitquant/data/__init__.py
bitquant/data/clss.py
bitquant/data/conv.py
bitquant/data/tools.py
bitquant/sql/__init__.py
bitquant/sql/clss.py
bitquant/sql/setup.py
bitquant/sql/stmt.py