Metadata-Version: 1.0
Name: bitquant
Version: 0.3.1
Summary: Bitcoin trade and exchange data miner
Home-page: http://rosspalmer.github.io/bitQuant/
Author: ross palmer
Author-email: UNKNOWN
License: MIT
Platform: UNKNOWN
